README.txt
setup.py
topp/__init__.py
topp.utils.egg-info/PKG-INFO
topp.utils.egg-info/SOURCES.txt
topp.utils.egg-info/dependency_links.txt
topp.utils.egg-info/entry_points.txt
topp.utils.egg-info/namespace_packages.txt
topp.utils.egg-info/not-zip-safe
topp.utils.egg-info/requires.txt
topp.utils.egg-info/top_level.txt
topp/utils/__init__.py
topp/utils/config.py
topp/utils/detag.py
topp/utils/eputils.py
topp/utils/error.py
topp/utils/filesystem.py
topp/utils/introspection.py
topp/utils/ip.py
topp/utils/memorycache.py
topp/utils/modules.py
topp/utils/orderedpersistentmapping.py
topp/utils/persistence.py
topp/utils/pretty_date.py
topp/utils/pretty_text.py
topp/utils/setup_command.py
topp/utils/testing.py
topp/utils/text.py
topp/utils/uri.py
topp/utils/wenvutils.py
topp/utils/zutils.py