Metadata-Version: 1.0
Name: topp.utils
Version: 0.5.1
Summary: utility library used for openplans.org
Home-page: https://svn.openplans.org/svn/topp.utils
Author: The Open Planning Project
Author-email: info@openplans.org
License: GPL
Keywords: topp openplans
Platform: UNKNOWN
